hdicoding/__init__.py
hdicoding/hdicoding.py
hdicoding-1.0.dist-info/METADATA
hdicoding-1.0.dist-info/WHEEL
hdicoding-1.0.dist-info/top_level.txt
hdicoding-1.0.dist-info/RECORD
