Metadata-Version: 2.1
Name: hdicoding
Version: 1.0
Summary: Python functions for controlling Arduino devices
Author: dain0113
Author-email: hdi5709@naver.com
Requires-Dist: pyserial
